lazyclone/__init__.py
lazyclone/console.py
lazyclone/git.py
lazyclone/github.py
lazyclone/program.py
lazyclone/repository.py
lazyclone-0.2.1.dist-info/WHEEL
lazyclone-0.2.1.dist-info/entry_points.txt
lazyclone-0.2.1.dist-info/METADATA
lazyclone-0.2.1.dist-info/RECORD
