Metadata-Version: 2.3
Name: lazyclone
Version: 0.2.1
Summary: Git clone but easier
Author: Oli
Author-email: Oli <oli@olillin.com>
License:                                  Apache License
Requires-Dist: inquirer>=3.4.1
Requires-Dist: rich>=14.2.0
Maintainer: Oli
Maintainer-email: Oli <oli@olillin.com>
Requires-Python: >=3.13
Project-URL: Bug Reports, https://github.com/olillin/lazyclone/issues
Project-URL: Source, https://github.com/olillin/lazyclone
